TS/TS.py
TS/__init__.py
TSvho-0.0.2.dist-info/METADATA
TSvho-0.0.2.dist-info/WHEEL
TSvho-0.0.2.dist-info/top_level.txt
TSvho-0.0.2.dist-info/RECORD
